Workbook

Sheet Income_statement
A1: Year | B1: Revenue | C1: COGS | D1: Gross Profit | E1: Operating Expenses | F1: Net Profit
A2: 2022 | B2: 4800000 | C2: 2850000 | D2: =B2-C2 -> 1950000 | E2: 900000 | F2: =D2-E2 -> 1050000
A3: 2023 | B3: 5600000 | C3: 3200000 | D3: =B3-C3 -> 2400000 | E3: 1050000 | F3: =D3-E3 -> 1350000
A4: 2024 | B4: 6500000 | C4: 3600000 | D4: =B4-C4 -> 2900000 | E4: 1200000 | F4: =D4-E4 -> 1700000

Sheet Balance_sheet
A1: Year | B1: Total Assets | C1: Total Liabilities | D1: Equity
A2: 2022 | B2: 7500000 | C2: 2800000 | D2: =B2-C2 -> 4700000
A3: 2023 | B3: 8500000 | C3: 3200000 | D3: =B3-C3 -> 5300000
A4: 2024 | B4: 9500000 | C4: 3500000 | D4: =B4-C4 -> 6000000

Sheet Ratio_Analysis
A1: Year | B1: Gross Margin | C1: Net Margin | D1: Debt Equity Ratio
A2: 2022 | B2: =Income_statement!D2/Income_statement!B2 -> 0.40625 | C2: =Income_statement!F2/Income_statement!B2 -> 0.21875 | D2: =Balance_sheet!C2/Balance_sheet!D2 -> 0.59574468
A3: 2023 | B3: =Income_statement!D3/Income_statement!B3 -> 0.42857143 | C3: =Income_statement!F3/Income_statement!B3 -> 0.24107143 | D3: =Balance_sheet!C3/Balance_sheet!D3 -> 0.60377358
A4: 2024 | B4: =Income_statement!D4/Income_statement!B4 -> 0.44615385 | C4: =Income_statement!F4/Income_statement!B4 -> 0.26153846 | D4: =Balance_sheet!C4/Balance_sheet!D4 -> 0.58333333

Sheet DASHBOARD
C2: Revenue Growth | J2: Profit Comparison | Q2: Margin Analysis
C3: 2022 | D3: 4800000 | J3: 2022 | K3: =G3-J3 -> -2022 | Q3: 0.40625 | R3: 0.59574468
C4: 2023 | D4: 5600000 | J4: 2023 | K4: =G4-J4 -> -2023 | Q4: 0.42857143 | R4: 0.60377358
C5: 2024 | D5: 6500000 | J5: 2024 | K5: =G5-J5 -> -2024 | Q5: 0.44615385 | R5: 0.58333333
